psychonaut/__init__.py
psychonaut/api/__init__.py
psychonaut/api/lexicons/app/__init__.py
psychonaut/api/lexicons/app/bsky/__init__.py
psychonaut/api/lexicons/app/bsky/actor/__init__.py
psychonaut/api/lexicons/app/bsky/actor/defs.py
psychonaut/api/lexicons/app/bsky/actor/get_profile.py
psychonaut/api/lexicons/app/bsky/actor/get_profiles.py
psychonaut/api/lexicons/app/bsky/actor/get_suggestions.py
psychonaut/api/lexicons/app/bsky/actor/profile.py
psychonaut/api/lexicons/app/bsky/actor/search_actors.py
psychonaut/api/lexicons/app/bsky/actor/search_actors_typeahead.py
psychonaut/api/lexicons/app/bsky/embed/__init__.py
psychonaut/api/lexicons/app/bsky/embed/external.py
psychonaut/api/lexicons/app/bsky/embed/images.py
psychonaut/api/lexicons/app/bsky/embed/record.py
psychonaut/api/lexicons/app/bsky/embed/record_with_media.py
psychonaut/api/lexicons/app/bsky/feed/__init__.py
psychonaut/api/lexicons/app/bsky/feed/defs.py
psychonaut/api/lexicons/app/bsky/feed/get_author_feed.py
psychonaut/api/lexicons/app/bsky/feed/get_likes.py
psychonaut/api/lexicons/app/bsky/feed/get_post_thread.py
psychonaut/api/lexicons/app/bsky/feed/get_posts.py
psychonaut/api/lexicons/app/bsky/feed/get_reposted_by.py
psychonaut/api/lexicons/app/bsky/feed/get_timeline.py
psychonaut/api/lexicons/app/bsky/feed/like.py
psychonaut/api/lexicons/app/bsky/feed/post.py
psychonaut/api/lexicons/app/bsky/feed/repost.py
psychonaut/api/lexicons/app/bsky/graph/__init__.py
psychonaut/api/lexicons/app/bsky/graph/block.py
psychonaut/api/lexicons/app/bsky/graph/follow.py
psychonaut/api/lexicons/app/bsky/graph/get_blocks.py
psychonaut/api/lexicons/app/bsky/graph/get_followers.py
psychonaut/api/lexicons/app/bsky/graph/get_follows.py
psychonaut/api/lexicons/app/bsky/graph/get_mutes.py
psychonaut/api/lexicons/app/bsky/graph/mute_actor.py
psychonaut/api/lexicons/app/bsky/graph/unmute_actor.py
psychonaut/api/lexicons/app/bsky/notification/__init__.py
psychonaut/api/lexicons/app/bsky/notification/get_unread_count.py
psychonaut-0.0.16.dist-info/LICENSE
psychonaut-0.0.16.dist-info/METADATA
psychonaut-0.0.16.dist-info/WHEEL
psychonaut-0.0.16.dist-info/entry_points.txt
psychonaut-0.0.16.dist-info/RECORD
