Metadata-Version: 2.1
Name: psychonaut
Version: 0.0.16
Summary: Python async client and TUI for bsky
Home-page: https://github.com/jbn/psychonaut
License: MIT
Author: generativist
Author-email: jbn@abreka.com
Requires-Python: >=3.10,<4.0
Classifier: License :: OSI Approved :: MIT License
Classifier: Programming Language :: Python :: 3
Classifier: Programming Language :: Python :: 3.10
Classifier: Programming Language :: Python :: 3.11
Provides-Extra: optimized
Requires-Dist: aiodns (>=3.0.0,<4.0.0)
Requires-Dist: aiohttp (>=3.8.4,<4.0.0)
Requires-Dist: carbox (>=0.0.1,<0.0.2)
Requires-Dist: cbor2 (>=5.4.6,<6.0.0)
Requires-Dist: click (>=8.1.3,<9.0.0)
Requires-Dist: dag-cbor (>=0.3.2,<0.4.0)
Requires-Dist: more-itertools (>=9.1.0,<10.0.0)
Requires-Dist: multiformats (>=0.2.1,<0.3.0)
Requires-Dist: pydantic (>=1.10.7,<2.0.0)
Requires-Dist: python-dateutil (>=2.8.2,<3.0.0)
Requires-Dist: python-dotenv (>=1.0.0,<2.0.0)
Requires-Dist: websockets (>=11.0.2,<12.0.0)
Project-URL: Documentation, https://github.com/jbn/psychonaut
Project-URL: Repository, https://github.com/jbn/psychonaut
